{
  "name": "kanarion-data",
  "version": "3.1.0",
  "database_version": "3.1",
  "schema_version": "1.0",
  "last_updated": "2026-03-02",
  "content_hash": "sha256:b8c56ee0a7e4ef80759b899635dbe658b3b56de850b59f3b9e80ead6bb382d40",
  "status": "alpha",
  "description": "Kanarion Online - Game Database (Source of Truth)",
  "compatibility": {
    "min_client_version": "0.1.0",
    "max_client_version": null
  },
  "authors": [
    "Marc-Elie Charleston"
  ],
  "repository": "https://github.com/Marc-ElieCharleston/kanarion_data"
}
