{
  "_meta": {
    "version": "3.1",
    "last_updated": "2026-01-20",
    "description": "Stats gagnees automatiquement a chaque niveau. Stats techniques = 0 (equipement/passifs seulement)"
  },

  "warrior": {
    "_comment": "Tank - HP/DEF/Armor growth",
    "hp": 12, "mp": 2,
    "hp_regen": 0.1, "mp_regen": 0,
    "hp_regen_combat": 0, "mp_regen_combat": 0,
    "atk": 2.0, "def": 1.5, "mag": 0.2,
    "armor": 0.8, "magic_resist": 0.3,
    "crit": 0, "crit_dmg": 0,
    "hit": 0, "flee": 0,
    "armor_pen": 0, "magic_pen": 0,
    "block_chance": 0, "parry_chance": 0,
    "effect_chance": 0, "effect_resist": 0,
    "debuff_duration": 0, "tenacity": 0, "buff_duration": 0,
    "damage_percent": 0, "damage_reduction": 0,
    "double_hit_chance": 0, "attack_speed": 0,
    "heal_power": 0, "shield_power": 0,
    "healing_received": 0,
    "lifesteal": 0, "spell_vamp": 0,
    "cast_speed": 0, "cooldown_reduction": 0,
    "luck": 0
  },

  "mage": {
    "_comment": "Glass cannon - MAG/MP growth",
    "hp": 6, "mp": 5,
    "hp_regen": 0.05, "mp_regen": 0.1,
    "hp_regen_combat": 0, "mp_regen_combat": 0.05,
    "atk": 0.3, "def": 0.3, "mag": 2.5,
    "armor": 0.2, "magic_resist": 0.8,
    "crit": 0, "crit_dmg": 0,
    "hit": 0, "flee": 0,
    "armor_pen": 0, "magic_pen": 0,
    "block_chance": 0, "parry_chance": 0,
    "effect_chance": 0, "effect_resist": 0,
    "debuff_duration": 0, "tenacity": 0, "buff_duration": 0,
    "damage_percent": 0, "damage_reduction": 0,
    "double_hit_chance": 0, "attack_speed": 0,
    "heal_power": 0, "shield_power": 0,
    "healing_received": 0,
    "lifesteal": 0, "spell_vamp": 0,
    "cast_speed": 0, "cooldown_reduction": 0,
    "luck": 0
  },

  "healer": {
    "_comment": "Support - MAG/MP/heal_power growth",
    "hp": 8, "mp": 4,
    "hp_regen": 0.08, "mp_regen": 0.08,
    "hp_regen_combat": 0, "mp_regen_combat": 0.03,
    "atk": 0.4, "def": 0.5, "mag": 2.0,
    "armor": 0.3, "magic_resist": 0.7,
    "crit": 0, "crit_dmg": 0,
    "hit": 0, "flee": 0,
    "armor_pen": 0, "magic_pen": 0,
    "block_chance": 0, "parry_chance": 0,
    "effect_chance": 0, "effect_resist": 0,
    "debuff_duration": 0, "tenacity": 0, "buff_duration": 0,
    "damage_percent": 0, "damage_reduction": 0,
    "double_hit_chance": 0, "attack_speed": 0,
    "heal_power": 0.5, "shield_power": 0.2,
    "healing_received": 0,
    "lifesteal": 0, "spell_vamp": 0,
    "cast_speed": 0, "cooldown_reduction": 0,
    "luck": 0
  },

  "archer": {
    "_comment": "Ranged DPS - ATK/HIT growth",
    "hp": 7, "mp": 2,
    "hp_regen": 0.06, "mp_regen": 0.05,
    "hp_regen_combat": 0, "mp_regen_combat": 0,
    "atk": 1.8, "def": 0.4, "mag": 0.4,
    "armor": 0.3, "magic_resist": 0.3,
    "crit": 0, "crit_dmg": 0,
    "hit": 0, "flee": 0,
    "armor_pen": 0, "magic_pen": 0,
    "block_chance": 0, "parry_chance": 0,
    "effect_chance": 0, "effect_resist": 0,
    "debuff_duration": 0, "tenacity": 0, "buff_duration": 0,
    "damage_percent": 0, "damage_reduction": 0,
    "double_hit_chance": 0, "attack_speed": 0,
    "heal_power": 0, "shield_power": 0,
    "healing_received": 0,
    "lifesteal": 0, "spell_vamp": 0,
    "cast_speed": 0, "cooldown_reduction": 0,
    "luck": 0
  },

  "rogue": {
    "_comment": "Assassin - ATK growth, technical stats from passifs/gear",
    "hp": 6, "mp": 2,
    "hp_regen": 0.05, "mp_regen": 0.05,
    "hp_regen_combat": 0, "mp_regen_combat": 0,
    "atk": 1.5, "def": 0.4, "mag": 0.4,
    "armor": 0.25, "magic_resist": 0.25,
    "crit": 0, "crit_dmg": 0,
    "hit": 0, "flee": 0,
    "armor_pen": 0, "magic_pen": 0,
    "block_chance": 0, "parry_chance": 0,
    "effect_chance": 0, "effect_resist": 0,
    "debuff_duration": 0, "tenacity": 0, "buff_duration": 0,
    "damage_percent": 0, "damage_reduction": 0,
    "double_hit_chance": 0, "attack_speed": 0,
    "heal_power": 0, "shield_power": 0,
    "healing_received": 0,
    "lifesteal": 0, "spell_vamp": 0,
    "cast_speed": 0, "cooldown_reduction": 0,
    "luck": 0
  },

  "artisan": {
    "_comment": "Utility - Balanced growth",
    "hp": 8, "mp": 3,
    "hp_regen": 0.08, "mp_regen": 0.06,
    "hp_regen_combat": 0, "mp_regen_combat": 0.02,
    "atk": 1.2, "def": 0.6, "mag": 1.0,
    "armor": 0.4, "magic_resist": 0.4,
    "crit": 0, "crit_dmg": 0,
    "hit": 0, "flee": 0,
    "armor_pen": 0, "magic_pen": 0,
    "block_chance": 0, "parry_chance": 0,
    "effect_chance": 0, "effect_resist": 0,
    "debuff_duration": 0, "tenacity": 0, "buff_duration": 0,
    "damage_percent": 0, "damage_reduction": 0,
    "double_hit_chance": 0, "attack_speed": 0,
    "heal_power": 0.2, "shield_power": 0.2,
    "healing_received": 0,
    "lifesteal": 0, "spell_vamp": 0,
    "cast_speed": 0, "cooldown_reduction": 0,
    "luck": 0
  }
}
